MANIFEST.in
README.md
setup.py
va_generator/__init__.py
va_generator/back_end_generator.py
va_generator/conf.json
va_generator/en_interaction_model_components.json
va_generator/generator.py
va_generator/interaction_model_generator.py
va_generator/it_interaction_model_components.json
va_generator/main.py
va_generator/syntax_checker.py
va_generator/validator.py
virtual_assistant_generator.egg-info/PKG-INFO
virtual_assistant_generator.egg-info/SOURCES.txt
virtual_assistant_generator.egg-info/dependency_links.txt
virtual_assistant_generator.egg-info/requires.txt
virtual_assistant_generator.egg-info/top_level.txt