Metadata-Version: 2.1
Name: virtual-assistant-generator
Version: 0.1.0
Summary: It provides access to a generator of virtual assistants extensions.
Home-page: https://github.com/mariaangelapellegrino/virtual_assistant_generator/va_generator
Author: Maria Angela Pellegrino
Author-email: mapellegrino@unisa.it
License: UNKNOWN
Platform: UNKNOWN
Classifier: Programming Language :: Python :: 3
Classifier: License :: OSI Approved :: MIT License
Classifier: Operating System :: OS Independent
Requires-Python: >=3.6
